openenv/__init__.py
openenv/env/__init__.py
openenv/env/env.py
openenv/util/__init__.py
openenv/util/math_utils.py
openenv/util/random_utils.py
openenv/util/time_utils.py
openenv-0.1.13.dist-info/LICENSE
openenv-0.1.13.dist-info/METADATA
openenv-0.1.13.dist-info/WHEEL
openenv-0.1.13.dist-info/top_level.txt
openenv-0.1.13.dist-info/RECORD
