Metadata-Version: 2.1
Name: openenv
Version: 0.1.13
Summary: A Python package consisting of open-source implemented environments for reinforcement learning.
Home-page: https://github.com/neo-derek/open-env
Author: Jianfeng Hou
Author-email: frankderekdick@gmail.com
License: UNKNOWN
Platform: UNKNOWN
Classifier: Programming Language :: Python :: 3
Classifier: License :: OSI Approved :: Apache Software License
Classifier: Operating System :: OS Independent
Requires-Python: >=3.6
